cdk_cloudformation_datadog_integrations_awsaccount/__init__.py
cdk_cloudformation_datadog_integrations_awsaccount/py.typed
cdk_cloudformation_datadog_integrations_awsaccount/_jsii/__init__.py
cdk_cloudformation_datadog_integrations_awsaccount/_jsii/datadog-integrations-awsaccount@1.0.0-alpha.7.jsii.tgz
cdk_cloudformation_datadog_integrations_awsaccount-1.0.0a7.dist-info/LICENSE
cdk_cloudformation_datadog_integrations_awsaccount-1.0.0a7.dist-info/METADATA
cdk_cloudformation_datadog_integrations_awsaccount-1.0.0a7.dist-info/WHEEL
cdk_cloudformation_datadog_integrations_awsaccount-1.0.0a7.dist-info/top_level.txt
cdk_cloudformation_datadog_integrations_awsaccount-1.0.0a7.dist-info/RECORD
