Metadata-Version: 2.1
Name: cdk-cloudformation-datadog-integrations-awsaccount
Version: 1.0.0a7
Summary: Datadog AWS Account Integration 1.0.0
Home-page: https://github.com/cdklabs/cdk-cloudformation.git
Author: Amazon Web Services
License: Apache-2.0
Project-URL: Source, https://github.com/cdklabs/cdk-cloudformation.git
Classifier: Intended Audience :: Developers
Classifier: Operating System :: OS Independent
Classifier: Programming Language :: JavaScript
Classifier: Programming Language :: Python :: 3 :: Only
Classifier: Programming Language :: Python :: 3.9
Classifier: Programming Language :: Python :: 3.10
Classifier: Programming Language :: Python :: 3.11
Classifier: Typing :: Typed
Classifier: License :: OSI Approved
Requires-Python: ~=3.9
License-File: LICENSE
Requires-Dist: aws-cdk-lib <3.0.0,>=2.211.0
Requires-Dist: constructs <11.0.0,>=10.4.2
Requires-Dist: jsii <2.0.0,>=1.113.0
Requires-Dist: publication >=0.0.3
Requires-Dist: typeguard <4.3.0,>=2.13.3
